[
  {
    "title": "Samsung Tipped To Make Advanced Cameras For iPhone 18 Pro Model: Know More - News18",
    "link": "https://www.news18.com/tech/samsung-tipped-to-make-advanced-cameras-for-iphone-18-pro-model-know-more-9179098.html",
    "pubDate": "Mon, 06 Jan 2025 08:02:43 GMT",
    "summary": "<h1>Samsung Tipped To Make Advanced Cameras For iPhone 18 Pro Model: Know More</h1>\n<p><strong>Date:</strong> January 06, 2025</p>\n<p><strong>Source:</strong> News18</p>\n<img src=\"https://images.news18.com/ibnlive/uploads/2021/07/1627283897_news18_logo-1200x800.jpg?impolicy=website&amp;width=360&amp;height=270\" alt=\"The iPhone 18 camera details should get people excited.\" />\n<figcaption>The iPhone 18 camera details should get people excited.</figcaption>\n<p>Samsung is looking to upgrade the camera technology for future iPhone models, with potential developments being observed for the iPhone 18 expected to launch in 2026.</p>\n<ul>\n  <li>Reports indicate that Samsung is developing a three-layer stacked sensor for the upcoming Apple iPhones.</li>\n  <li>This could mark a shift from Sony, which has had exclusive contracts for Apple’s camera sensors for over a decade.</li>\n  <li>The new sensor is designed to provide faster signal processing speeds and improved image quality, especially in low-light conditions.</li>\n  <li>The iPhone 18 may feature a 48-MP sensor and Apple’s next-gen A20 chipset.</li>\n  <li>Samsung is also developing a 500MP camera sensor for its own Galaxy devices.</li>\n</ul>\n<blockquote>“This new sensor, which reportedly has a PD-TR-Logic configuration, is expected to outperform Sony's Exmor RS image sensors.”</blockquote>\n<p>In summary, the collaboration between Samsung and Apple on the iPhone 18's camera technology could lead to significant advancements in mobile photography.</p>",
    "significance": [
      {
        "type": "Scale",
        "score": 8
      },
      {
        "type": "Impact",
        "score": 7
      },
      {
        "type": "Novelty",
        "score": 6
      },
      {
        "type": "Positivity",
        "score": 8
      },
      {
        "type": "Credibility",
        "score": 9
      },
      {
        "type": "Urgency",
        "score": 2
      },
      {
        "type": "Diversity of Impact",
        "score": 7
      },
      {
        "type": "Long-Term Significance",
        "score": 8
      },
      {
        "type": "Public Engagement",
        "score": 6
      },
      {
        "type": "Sentiment Intensity",
        "score": 5
      },
      {
        "type": "Geopolitical Significance",
        "score": 7
      },
      {
        "type": "Contextual Significance",
        "score": 9
      },
      {
        "type": "Economic Impact",
        "score": 8
      }
    ],
    "newTitle": "Samsung Tipped To Make Advanced Cameras For iPhone 18 Pro Model: Know More"
  },
  {
    "title": "Samsung Galaxy S25, Galaxy S25 Ultra Leaked Renders Suggest Colour Options - Gadgets 360",
    "link": "https://www.gadgets360.com/mobiles/news/samsung-s25-ultra-design-expected-colour-options-leak-galaxy-report-7410131",
    "pubDate": "Mon, 06 Jan 2025 08:00:25 GMT",
    "summary": "<h1>Samsung Galaxy S25 and S25 Ultra Leaked Renders Show New Colors</h1><p><strong>Publication Date:</strong> January 5, 2025 <strong>Source:</strong> Gizmochina</p><img src=\"https://i.gadgets360cdn.com/large/samsung_galaxy_s25_ultra_gizmochina_inline_1736148251204.jpg\" alt=\"Samsung Galaxy S25 Ultra\" /><figcaption>Samsung Galaxy S25 (left) and Galaxy S25 Ultra (right). Photo Credit: Gizmochina</figcaption><p>The Samsung Galaxy S25 series is expected to launch globally this month, showcasing the Galaxy S25, S25+, and the Ultra variant, featuring Qualcomm's Snapdragon 8 Elite chipset.</p><ul><li>The leaked renders reveal a blue color option called Icy Blue for the Galaxy S25 and Titanium Blue for the S25 Ultra.</li><li>Both models feature a design that supports magnetic wireless charging with a MagSafe-like ring.</li><li>The Galaxy S25 series will have slim bezels and centered hole-punch front cameras.</li><li>Expected color options include diverse choices such as mint, coral red, and titanium colors for the Ultra variant.</li></ul><blockquote>\"Samsung Galaxy Unpacked 2025 Could Take Place on January 22\"</blockquote><p>The leaks keep building anticipation for the launch of these new flagship models.</p>",
    "significance": [
      {
        "type": "Scale",
        "score": 8
      },
      {
        "type": "Impact",
        "score": 7
      },
      {
        "type": "Novelty",
        "score": 6
      },
      {
        "type": "Positivity",
        "score": 5
      },
      {
        "type": "Credibility",
        "score": 9
      },
      {
        "type": "Urgency",
        "score": 4
      },
      {
        "type": "Diversity of Impact",
        "score": 8
      },
      {
        "type": "Long-Term Significance",
        "score": 6
      },
      {
        "type": "Public Engagement",
        "score": 5
      },
      {
        "type": "Sentiment Intensity",
        "score": 3
      },
      {
        "type": "Geopolitical Significance",
        "score": 7
      },
      {
        "type": "Contextual Significance",
        "score": 5
      },
      {
        "type": "Economic Impact",
        "score": 6
      }
    ],
    "newTitle": "Samsung Galaxy S25 and S25 Ultra Leaked Renders Show New Colors"
  },
  {
    "title": "Redmi 14C 5G launched: Unboxing, quick review of affordable 5G phone from Xiaomi with Qualcomm chip, 50MP camera - The Financial Express",
    "link": "https://www.financialexpress.com/life/technology-redmi-14c-5g-launched-unboxing-quick-review-of-affordable-5g-phone-from-xiaomi-with-qualcomm-chip-50mp-camera-3708156/",
    "pubDate": "Mon, 06 Jan 2025 07:58:40 GMT",
    "summary": "<h1>Redmi 14C 5G launched: Unboxing, quick review of affordable 5G phone from Xiaomi with Qualcomm chip, 50MP camera</h1><p><strong>Date & Source:</strong> January 10, 2025, Financial Express</p><figure><img loading=\"lazy\" decoding=\"async\" width=\"800\" height=\"533\" src=\"https://www.financialexpress.com/wp-content/uploads/2025/01/REDMI-14C24.jpg\" alt=\"Redmi 14C 5G quick review\"><figcaption>Redmi 14C 5G has a large 6.88-inch display. (Photo: Saurabh Singh)</figcaption></figure><p>Xiaomi has launched the Redmi 14C 5G smartphone in India, enhancing its 5G lineup with a more powerful and efficient device designed for mass accessibility.</p><ul><li>The Redmi 14C is available in 4/64GB, 4/128GB, and 6/128GB variants priced at Rs 9,999, Rs 10,999, and Rs 11,999 respectively.</li><li>It features Qualcomm's Snapdragon 4 Gen 2 processor for improved performance over the Redmi A4.</li><li>The smartphone supports fast download speeds of up to 2.5 Gbps on 5G networks.</li><li>Camera specifications include a 50MP rear camera and an 8MP front camera.</li><li>It has a large 6.88-inch LCD display with a 720p resolution and a 120Hz refresh rate.</li><li>The device is powered by a 5160 mAh battery, with a bundled 33W charger.</li></ul><blockquote>“If the Redmi A4 5G caught your attention, the Redmi 14C 5G is a no-brainer.”</blockquote><p>The Redmi 14C 5G combines affordability with impressive features, solidifying Xiaomi's commitment to making 5G accessible for all.</p>",
    "significance": [
      {
        "type": "Scale",
        "score": 8
      },
      {
        "type": "Impact",
        "score": 7
      },
      {
        "type": "Novelty",
        "score": 6
      },
      {
        "type": "Positivity",
        "score": 8
      },
      {
        "type": "Credibility",
        "score": 9
      },
      {
        "type": "Urgency",
        "score": 5
      },
      {
        "type": "Diversity of Impact",
        "score": 7
      },
      {
        "type": "Long-Term Significance",
        "score": 6
      },
      {
        "type": "Public Engagement",
        "score": 7
      },
      {
        "type": "Sentiment Intensity",
        "score": 7
      },
      {
        "type": "Geopolitical Significance",
        "score": 5
      },
      {
        "type": "Contextual Significance",
        "score": 4
      },
      {
        "type": "Economic Impact",
        "score": 6
      }
    ],
    "newTitle": "Redmi 14C 5G Launched: Affordable 5G Smartphone with Impressive Specs"
  },
  {
    "title": "Apple’s AI notification feature in iOS 18.1 under fire for errors - Communications Today",
    "link": "https://www.communicationstoday.co.in/apples-ai-notification-feature-in-ios-18-1-under-fire-for-errors/",
    "pubDate": "Mon, 06 Jan 2025 07:51:03 GMT",
    "summary": null,
    "significance": null,
    "newTitle": null
  },
  {
    "title": "OnePlus 13 to get iPhone-inspired magnetic cases: Here's how you can attach accessories - HT Tech",
    "link": "https://news.google.com/rss/articles/CBMi4wFBVV95cUxPUldOVlZOY1NUcTlpQ2tCTmM1VG80d2pFRUhlUG0wdlN5bWNjenZLQi1OanBEcHI2NnpnUHpQOERCNHUwX05tLWZwLXlRVmZpZVNwVGQzU0lhazZMUExjZUhGcWx4YVltS0Z2QWJFYTJPVGNpTEZOSS1tcmN0THdDZ0l2VHFvS1BwY01hTDc0enhMNVl5YTFTU3JMY0FuQmxEX1BWelF1THcwNTNmQlNKX2FVMTNneWRlWnRhZHFIZDhXMlVwZlRsTWtzaVZHbG0yTU5pTk5yckwtMjhyYlFieGJFY9IB6AFBVV95cUxNbW1Yc3BqTTREQjRzV1dvTlE4ZTJFc0d2cndSalpmb2o0T1NCT3pjYWxYUklnUjdydEVYd25iQTJCRU14aU5vVUF6dzh6U0lGMklnOHZnaWJ3MGltOHZNQzlkc3lCWGg5cVA5Y0htZmxtUDZvX2dBT2xIRXUwTWxBTllBenVPX3ZEc3poSmJOazNncGJOWUVqRTh6SjZ1VGJNQUxZM3d6Q1RoVkFKQ0tWTzBqOHdnUk9MTTZ6NzNXeVMzZ2JtZFRZX0J6YWdWTURxcHFWdEpSN2x1eXh4ZDNyU245UmpuNElI?oc=5&hl=en-US&gl=US&ceid=US:en",
    "pubDate": "Mon, 06 Jan 2025 07:43:28 GMT",
    "summary": null,
    "significance": null,
    "newTitle": null
  },
  {
    "title": "realme 14 Pro Series 5G set to launch on January 16 with colour changing design - CNBCTV18",
    "link": "https://news.google.com/rss/articles/CBMi0wFBVV95cUxOZkdDSHZiNkw2c3NadEFpQWRBeHpOX2YwZDJjUDZlZWNNdWlJd3JGcnpIbVhNVkNIMFZGc3ZINGNibHh1ZnBYTEpySTJYOWVNck4tZ0VFMUZmVnFhTlJCMzliN0tlYU5HNDZSbXBreXpKTTI5MENESE1idGV0RWlJN2FtTzh6c2duUEVJN1JfU1FodzFXQ1VsYkNQTk9vY2tCWHMzNlBrajR3R1dTNXRGbnFzekVQUVEzNUVGQXhnT0FpT2JwZ1loSEFJcTJ6MTRFdUdr0gHYAUFVX3lxTE93d01yTzJSVExSM3RwMzR4bENPSG8tWmVfc1FtSWNqbDZUcFM0UUl0X0FMOUlIRFEtT05IMWNweWtoLTZZMlBETElFMU43NFRJck9NcWVhbVFYaVpTbGY3YmM1Z2xTaWtWTmVTbFRpMXlsaHk2OUNwd3ZhcFFSQmNYamhwMGRxd29Yanh3R0txNmdTUkg1TGRkdi1BaTlBYVFFc1VhaU41N1BUSXdtUmd3dzdwOWFScmhGZXE3WW5hNVdGajRqeF9tZmluNEFGRjZZd2tPdVlHRA?oc=5&hl=en-US&gl=US&ceid=US:en",
    "pubDate": "Mon, 06 Jan 2025 07:40:19 GMT",
    "summary": null,
    "significance": null,
    "newTitle": null
  },
  {
    "title": "Samsung Galaxy S25 Ultra vs OnePlus 13: Price In India, Dubai, USA, Launch Date, All Leaks - Times Now",
    "link": "https://news.google.com/rss/articles/CBMi9AFBVV95cUxNR1NMTFVtQkV5MWFEaUFTU2taWGV3eGlpV3RhUGRZclBBcF9VQWJIV2pXVnVIaDZnTDVkSU45QXV5OU5Zay01ekdsYmFlSjZCQjF6TXE1RWV4LUszZ0w1Yk9KcHdER1d3bEFzbHVrWlJDbXVtWUUtaGMyclIxdnN5RHpZdnQ5UWxvdXo3UHhRVDhTLTl5V2o1QzBGejBfeEJrSjI5bDJxMWxZS0x0LTViVlhuRHZ4dXg2NWFvd2p3UEJfclRSTE1RTnhGSFpFMVltSGE4OWc5UU1BZE9qSHNhdkpZOVFwakNaMTVRVVdFRVp3Rk1h0gH0AUFVX3lxTE1HU0xMVW1CRXkxYURpQVNTa1pYZXd4aWlXdGFQZFlyUEFwX1VBYkhXaldWdUhoNmdMNWRJTjlBdXk5TllrLTV6R2xiYWVKNkJCMXpNcTVFZXgtSzNnTDViT0pwd0RHV3dsQXNsdWtaUkNtdW1ZRS1oYzJyUjF2c3lEell2dDlRbG91ejdQeFFUOFMtOXlXajVDMEZ6MF94QmtKMjlsMnExbFlLTHQtNWJWWG5Ednh1eDY1YW93andQQl9yVFJMTVFOeEZIWkUxWW1IYTg5ZzlRTUFkT2pIc2F2Slk5UXBqQ1oxNVFVV0VFWndGTWE?oc=5&hl=en-US&gl=US&ceid=US:en",
    "pubDate": "Mon, 06 Jan 2025 07:19:50 GMT",
    "summary": null,
    "significance": null,
    "newTitle": null
  },
  {
    "title": "Garena Free Fire Max redeem codes released today offer variety of free rewards - India TV News",
    "link": "https://www.indiatvnews.com/technology/gaming/garena-free-fire-max-redeem-codes-released-today-offer-variety-of-free-rewards-2025-01-06-969787",
    "pubDate": "Mon, 06 Jan 2025 07:13:15 GMT",
    "summary": "<h1>Garena Free Fire Max Redeem Codes Released Today Offer Free Rewards</h1><p><strong>Publication Date:</strong> January 6, 2025<br><strong>Source:</strong> India TV News</p><img src=\"https://resize.indiatvnews.com/en/centered/newbucket/1200_675/2025/01/free-fire-redeem-codes-1736146099.webp\" alt=\"Free Fire redeem codes\" width=\"1200\" height=\"675\"><figcaption>Free Fire redeem codes</figcaption><p>Players can unlock a variety of in-game rewards with the latest redeem codes released for Free Fire Max. These rewards significantly enhance gameplay.</p><h2>Key Points:</h2><ul><li>Redeem codes for Free Fire Max provide various in-game rewards.</li><li>Players redeem codes on the Free Fire website with codes consisting of 12-16 alphanumeric characters.</li><li>The codes are time-sensitive and may be region-restricted.</li><li>Detailed list of redeem codes provided for January 6, 2025.</li><li>Instructions on how to redeem codes are given for players.</li><li>Free Fire has been banned in India since 2022, but Free Fire Max remains available.</li></ul><blockquote>“If everything goes smoothly, you'll receive your rewards within 24 hours after redeeming the code successfully.”</blockquote><p>This update from Garena showcases continuous efforts to engage players despite previous setbacks with the game's availability.</p>",
    "significance": [
      {
        "type": "Scale",
        "score": 7
      },
      {
        "type": "Impact",
        "score": 6
      },
      {
        "type": "Novelty",
        "score": 5
      },
      {
        "type": "Positivity",
        "score": 8
      },
      {
        "type": "Credibility",
        "score": 9
      },
      {
        "type": "Urgency",
        "score": 4
      },
      {
        "type": "Diversity of Impact",
        "score": 6
      },
      {
        "type": "Long-Term Significance",
        "score": 5
      },
      {
        "type": "Public Engagement",
        "score": 7
      },
      {
        "type": "Sentiment Intensity",
        "score": 5
      },
      {
        "type": "Geopolitical Significance",
        "score": 4
      },
      {
        "type": "Contextual Significance",
        "score": 6
      },
      {
        "type": "Economic Impact",
        "score": 7
      }
    ],
    "newTitle": "Garena Free Fire Max Redeem Codes Released Today Offer Free Rewards"
  },
  {
    "title": "It is revealed that vivo is preparing Dimensity 9400 tablet: it will be released with X200 Ultra in April – Passionategeekz - Passionategeekz",
    "link": "https://passionategeekz.com/it-is-revealed-that-vivo-is-preparing-dimensity-9400-tablet-it-will-be-released-with-x200-ultra-in-april-passionategeekz/",
    "pubDate": "Mon, 06 Jan 2025 07:05:19 GMT",
    "summary": "<h1>Vivo Plans to Launch Dimensity 9400 Tablet Alongside X200 Ultra in April</h1><p><strong>Publication Date:</strong> Not specified <strong>Source:</strong> Passionategeekz</p><img src=\"http://img.cnmo.com/2261_600x1000/2260471.jpg\" alt=\"Vivo Dimensity 9400 Tablet\" /><figcaption>Vivo Dimensity 9400 Tablet Reveal</figcaption><p>Vivo is set to unveil a new tablet powered by the MediaTek Dimensity 9400 chip, scheduled for release alongside the vivo X200 Ultra in April 2025.</p><ul><li>Vivo is currently selling multiple tablet models including the vivo Pad 3, vivo Pad Air, and iQOO Pad Air.</li><li>The Dimensity 9400 chip was launched globally by the vivo X200 series and is described as a flagship 5G smart AI chip.</li><li>The device will be part of a product lineup that includes three flagship phones and a round vivo watch.</li><li>The vivo X200 Ultra will feature the Qualcomm Snapdragon 8 Elite mobile platform, while the “S” series models will retain the Dimensity 9400.</li></ul><blockquote>“The MediaTek Dimensity 9400 chip is the second generation full-core SoC of the Dimensity series.”</blockquote><p>This upcoming launch highlights Vivo's commitment to advancing its tablet offerings in the competitive tech market.</p>",
    "significance": [
      {
        "type": "Scale",
        "score": 8
      },
      {
        "type": "Impact",
        "score": 7
      },
      {
        "type": "Novelty",
        "score": 6
      },
      {
        "type": "Positivity",
        "score": 5
      },
      {
        "type": "Credibility",
        "score": 9
      },
      {
        "type": "Urgency",
        "score": 4
      },
      {
        "type": "Diversity of Impact",
        "score": 7
      },
      {
        "type": "Long-Term Significance",
        "score": 6
      },
      {
        "type": "Public Engagement",
        "score": 8
      },
      {
        "type": "Sentiment Intensity",
        "score": 5
      },
      {
        "type": "Geopolitical Significance",
        "score": 6
      },
      {
        "type": "Contextual Significance",
        "score": 5
      },
      {
        "type": "Economic Impact",
        "score": 7
      }
    ],
    "newTitle": "Vivo Plans to Launch Dimensity 9400 Tablet Alongside X200 Ultra in April"
  },
  {
    "title": "Redmi 14C 5G launched with 120 Hz refresh rate and Snapdragon processor for budget buyers in India - The Hindu",
    "link": "https://news.google.com/rss/articles/CBMigAJBVV95cUxOTlJFV3ZnekU1VHp0eFFQNXRNNDNkLWtJUUt5TDVaTWkzRnFGUXNnSDZ1SHBUOWJBOWF4QnJZT0QtTXVibG9GRDNKQlEzWEZvQXM0R1JwcWdRN0R2SzIzeVRtbVVlLTMzS3E1d0lPV2NMUHoyYk81QkRSQXVQWnZHRllWVHpGTnF1TnpKVXFkcHJpZkVTOHROVmdTRDRad3JPMGh6V1RSNE5fZnVIUmV0djhfVEd4d2g1cElDajQ5Q3hRblU0cjRnWmxrOE1KQlh6QnZQcHlIS1Fqakw1ZTc1OXZhN1NMSEdoQ0pEZXp5ZkJId09ON3hjazJ5ZFBnSmh20gGHAkFVX3lxTE5fSWhidXcxVDJKTGpqTnlZeXBWVHZaT3lESW5QUm9NeWtwWlFsTnZLQzk0MWx4YTRkb1pmb2J1UWJDWjJsNDdJaDJJMFJFeFZYUkQtOXMzMmxLNVREX185aTZxazJ4THVTZEd6QzJvdWZpdzllbTA1Z3U3OUNhZDk4TEhJQ2RVQjdSLVhfVGREUEN3Y1VyX2RQazAyMmQtWUFkVDk1Um1YNDdxS3l0NmR2R1kwTXJrWmx4QlBaaXhHdHJMb2loWkVsTEFPU3BvRktsaXBLSDZzWFd5YmFsMVpFblFOOFRSaWlDUFFsU09zMGYzbWI3ekV2WXpUMm16eENwbVktWF9F?oc=5&hl=en-US&gl=US&ceid=US:en",
    "pubDate": "Mon, 06 Jan 2025 07:01:00 GMT",
    "summary": null,
    "significance": null,
    "newTitle": null
  },
  {
    "title": "CES 2025: LG brings OLED evo TVs with built-in AI, new lifestyle projectors - Business Standard",
    "link": "https://www.business-standard.com/technology/tech-news/ces-2025-lg-brings-oled-evo-tvs-with-built-in-ai-new-lifestyle-projectors-125010600351_1.html",
    "pubDate": "Mon, 06 Jan 2025 06:59:50 GMT",
    "summary": "<h1>LG Unveils OLED evo TVs and Lifestyle Projectors at CES 2025</h1><p><strong>Publication Date:</strong> January 2025</p><p><strong>Source:</strong> Consumer Electronics Show</p><p>LG has introduced its latest 2025 OLED evo TV lineup and new lifestyle projectors, showcasing advancements in AI-powered features and display technology.</p><img src=\"path_to_image.jpg\" alt=\"LG OLED evo TV\"/><figcaption>LG's new OLED evo TV at CES 2025.</figcaption><p>Key highlights include:</p><ul><li>Introduction of true wireless OLED evo M5 and OLED evo G5 models.</li><li>Brightness Booster Ultimate technology for enhanced brightness.</li><li>AI features including AI Welcome, AI Voice ID, and AI Search for personalization.</li><li>New lifestyle projectors combining Bluetooth speakers and LED mood lamps.</li></ul><blockquote>“The new OLED evo 4K TVs include an updated Filmmaker Mode with Ambient Light Compensation.”</blockquote><p>This launch marks a significant step in LG's product innovation, focusing on enhancing the user experience through technology and design.</p>",
    "significance": [
      {
        "type": "Scale",
        "score": 8
      },
      {
        "type": "Impact",
        "score": 7
      },
      {
        "type": "Novelty",
        "score": 6
      },
      {
        "type": "Positivity",
        "score": 9
      },
      {
        "type": "Credibility",
        "score": 9
      },
      {
        "type": "Urgency",
        "score": 5
      },
      {
        "type": "Diversity of Impact",
        "score": 6
      },
      {
        "type": "Long-Term Significance",
        "score": 8
      },
      {
        "type": "Public Engagement",
        "score": 7
      },
      {
        "type": "Sentiment Intensity",
        "score": 6
      },
      {
        "type": "Geopolitical Significance",
        "score": 5
      },
      {
        "type": "Contextual Significance",
        "score": 7
      },
      {
        "type": "Economic Impact",
        "score": 7
      }
    ],
    "newTitle": "LG Unveils OLED evo TVs and Lifestyle Projectors at CES 2025"
  },
  {
    "title": "OnePlus 13, OnePlus 13R Launches Tomorrow In India: Price, Full Specs, How To Watch Live Event On Jan 7 - Times Now",
    "link": "https://www.timesnownews.com/technology-science/gadgets/oneplus-13-oneplus-13r-launch-date-in-india-price-full-specs-how-to-watch-live-event-on-jan-7-article-116985518",
    "pubDate": "Mon, 06 Jan 2025 06:52:23 GMT",
    "summary": "<h1>OnePlus 13 and OnePlus 13R Launching Tomorrow in India</h1><p><strong>Publication Date:</strong> January 6, 2025 &nbsp; <strong>Source:</strong> TNN</p><img loading=\"lazy\" src=\"https://static.tnn.in/thumb/msid-116985450,thumbsize-739291,width-1280,height-720,resizemode-75/116985450.jpg\" alt=\"OnePlus 13 Series\" title=\"OnePlus 13 Series\"><figcaption>OnePlus 13 Series</figcaption><p>The OnePlus 13 series is set to debut in India tomorrow, featuring the flagship OnePlus 13 and the budget-friendly OnePlus 13R.</p><ul><li>The launch event will be streamed live on January 7, 2025, at 7:30 PM IST via OnePlus’s official website and YouTube channel.</li><li>The expected price of the OnePlus 13 is under Rs 70,000, while the OnePlus 13R may be priced under Rs 50,000.</li><li>Both models have a refreshed design with flat displays, diverging from the previous curved ones.</li><li>The OnePlus 13 is powered by the Snapdragon 8 Elite chipset; the 13R uses Snapdragon 8 Gen 3.</li><li>Both devices feature a 6,000mAh battery and fast-charging support.</li><li>The OnePlus 13 guarantees 4 years of Android updates, while the 13R promises 3 years.</li></ul><blockquote>“Both the OnePlus 13 and the OnePlus 13R aim to provide flagship performance at competitive prices.”</blockquote><p>In conclusion, the OnePlus 13 series aims to position itself strongly in the Indian smartphone market with offerings that cater to both premium and budget-conscious consumers.</p>",
    "significance": [
      {
        "type": "Scale",
        "score": 8
      },
      {
        "type": "Impact",
        "score": 7
      },
      {
        "type": "Novelty",
        "score": 6
      },
      {
        "type": "Positivity",
        "score": 5
      },
      {
        "type": "Credibility",
        "score": 9
      },
      {
        "type": "Urgency",
        "score": 4
      },
      {
        "type": "Diversity of Impact",
        "score": 5
      },
      {
        "type": "Long-Term Significance",
        "score": 7
      },
      {
        "type": "Public Engagement",
        "score": 6
      },
      {
        "type": "Sentiment Intensity",
        "score": 5
      },
      {
        "type": "Geopolitical Significance",
        "score": 5
      },
      {
        "type": "Contextual Significance",
        "score": 6
      },
      {
        "type": "Economic Impact",
        "score": 7
      }
    ],
    "newTitle": "OnePlus 13 and OnePlus 13R Launching Tomorrow in India"
  },
  {
    "title": "Flipkart Offer: Smart TVs Available Under Just Rs 9,000 – Hurry! Grab THESE Best Deals At Half Price NOW - News24",
    "link": "https://news24online.com/tech/flipkart-offer-smart-tvs-available-under-just-rs-9000-hurry-grab-these-best-deals-at-half-price-now/432493/",
    "pubDate": "Mon, 06 Jan 2025 06:20:23 GMT",
    "summary": "<h1>Flipkart Offer: Smart TVs Available Under Just Rs 9,000 – Hurry! Grab THESE Best Deals At Half Price NOW</h1> <p><strong>Date: January 06, 2025 | Source: News24</strong></p> <img src=\"https://rukminim2.flixcart.com/image/416/416/xif0q/television/q/s/k/-original-imah3vhtb9jn2fk6.jpeg?q=70&amp;crop=false\" alt=\"Infinix 80 cm (32 inch) HD Ready LED Smart Linux TV 2024 Edition\"> <figcaption>Infinix 80 cm (32 inch) HD Ready LED Smart Linux TV 2024 Edition</figcaption> <p>Flipkart is presenting fantastic deals on 32-inch smart TVs, all priced below INR 9,000, with discounts reaching up to 57%. Here are the top picks of the best deals available:</p> <ul> <li><strong>Infinix 32-inch HD Ready LED Smart TV:</strong> Price: INR 8,499 (originally INR 16,999), with EMI discounts available.</li> <li><strong>KODAK Special Edition 32-inch HD Ready LED Smart TV:</strong> Price after up to 44% discount, with EMI discounts available.</li> <li><strong>TCL 32-inch HD Ready LED Smart Android TV:</strong> Price: INR 8,990 (originally INR 20,990), featuring an incredible 57% discount.</li> </ul> <p>As the festive season approaches, these deals present an excellent opportunity for upgrading your entertainment setup.</p> <blockquote>“A brilliant blend of affordability and superior technology is literally at your fingertips.”</blockquote>",
    "significance": [
      {
        "type": "Scale",
        "score": 9
      },
      {
        "type": "Impact",
        "score": 8
      },
      {
        "type": "Novelty",
        "score": 7
      },
      {
        "type": "Positivity",
        "score": 8
      },
      {
        "type": "Credibility",
        "score": 9
      },
      {
        "type": "Urgency",
        "score": 6
      },
      {
        "type": "Diversity of Impact",
        "score": 7
      },
      {
        "type": "Long-Term Significance",
        "score": 8
      },
      {
        "type": "Public Engagement",
        "score": 8
      },
      {
        "type": "Sentiment Intensity",
        "score": 7
      },
      {
        "type": "Geopolitical Significance",
        "score": 6
      },
      {
        "type": "Contextual Significance",
        "score": 5
      },
      {
        "type": "Economic Impact"
      }
    ],
    "newTitle": "Flipkart Offers Amazing Deals on Smart TVs Under Rs 9,000"
  },
  {
    "title": "iPhone SE4 to be branded as iPhone 16E, feature same design as iPhone 14, single rear camera - Firstpost",
    "link": "https://www.firstpost.com/tech/iphone-se4-to-be-branded-as-iphone-16e-feature-same-design-as-iphone-14-single-rear-camera-13850214.html",
    "pubDate": "Mon, 06 Jan 2025 06:15:29 GMT",
    "summary": "<h1>iPhone SE4 to be Branded as iPhone 16E with iPhone 14 Design</h1><p><strong>Publication Date:</strong> Not specified <strong>Source:</strong> Firstpost</p><img src=\"https://images.firstpost.com/uploads/2025/01/iPhone-SE4-to-be-branded-as-iPhone-16E-feature-same-design-as-iPhone-14-single-rear-camera-2025-01-5b0691e4949b6d51189e8d4aa0b54258-1200x675.jpg?im=FitAndFill=(596,336)\" alt=\"iPhone SE4 to be branded as iPhone 16E, feature same design as iPhone 14, single rear camera\" title=\"iPhone SE4 to be branded as iPhone 16E, feature same design as iPhone 14, single rear camera\"><figcaption>Image Credit: Pexels</figcaption><p>Apple's upcoming budget-friendly iPhone, rumored as the iPhone SE4, is now expected to be called the iPhone 16E, featuring a modern design and significant upgrades.</p><ul><li>The iPhone 16E is rumored to feature the sleek design of the iPhone 14, including a 6.1-inch OLED display and Face ID notch.</li><li>It will likely be powered by the A18 chip and have a single 48MP rear camera.</li><li>This device marks the first major design change for Apple's budget iPhone in five years.</li><li>The launch price might be around $499, but analysts predict it could be priced higher based on its features.</li><li>The name change from SE to 16E could help position the device in a more competitive mid-range market.</li></ul><blockquote>“Switching to the iPhone 16E branding might make sense for Apple’s marketing strategy.”</blockquote><p>The iPhone 16E appears set to break away from traditional budget offerings and may redefine Apple's approach to affordability in smartphones.</p>",
    "significance": [
      {
        "type": "Scale",
        "score": 8
      },
      {
        "type": "Impact",
        "score": 7
      },
      {
        "type": "Novelty",
        "score": 6
      },
      {
        "type": "Positivity",
        "score": 5
      },
      {
        "type": "Credibility",
        "score": 9
      },
      {
        "type": "Urgency",
        "score": 3
      },
      {
        "type": "Diversity of Impact",
        "score": 7
      },
      {
        "type": "Long-Term Significance",
        "score": 8
      },
      {
        "type": "Public Engagement",
        "score": 6
      },
      {
        "type": "Sentiment Intensity",
        "score": 5
      },
      {
        "type": "Geopolitical Significance",
        "score": 4
      },
      {
        "type": "Contextual Significance",
        "score": 6
      },
      {
        "type": "Economic Impact",
        "score": 8
      }
    ],
    "newTitle": "iPhone SE4 to be Branded as iPhone 16E with iPhone 14 Design"
  },
  {
    "title": "Technical note on steps in baseline quantification for ARR carbon finance projects using remote sensing and GIS. - TERI",
    "link": "https://news.google.com/rss/articles/CBMitwFBVV95cUxQeTNTU29tTktyOHVnN2tZWWhnWXhyNlhYTzItMWtLOVNkOEt4VFZOSTdzZ1dwNWtiVi1qcElYTXZVWjBudThHbEFwRnRyRGpJT2dqQXJSR3lxVDItRFNzcTlmRk5iaXZ2Y0dSYWJfbHlvYmZaSEtCZ1RMbWVBeU5WUDdPekZpanBMOXVsemktQWlmNGpEVlR4cmJfcFlONk5UbkR0elB4cEhySUIwUWZNSWxQZXBqUGc?oc=5&hl=en-US&gl=US&ceid=US:en",
    "pubDate": "Mon, 06 Jan 2025 06:08:22 GMT",
    "summary": null,
    "significance": null,
    "newTitle": null
  },
  {
    "title": "realme 14 Pro Series 5G launching in India on January 16th - FoneArena",
    "link": "https://www.fonearena.com/blog/443296/realme-14-pro-series-5g-india-launch-date.html",
    "pubDate": "Mon, 06 Jan 2025 06:04:45 GMT",
    "summary": "<h1>realme 14 Pro Series 5G Launching in India on January 16th</h1><p><strong>Date:</strong> January 16, 2025 <strong>Source:</strong> FoneArena</p><img src=\"https://images.fonearena.com/blog/wp-content/uploads/2025/01/realme-14-Pro-Series-5G-India-launch-date-1024x410.jpg\" alt=\"realme 14 Pro Series 5G Launch Image\"><figcaption>Launch of realme 14 Pro Series 5G in India</figcaption><p>realme has announced the upcoming launch of its 14 Pro Series 5G smartphones in India, highlighting innovative features and unique design elements that emphasize the brand's commitment to technological advancement.</p><ul><li>The 14 Pro Series 5G includes the world’s first smartphone with cold-sensitive color-changing technology in the Pearl White variant.</li><li>Two India-exclusive colors, Bikaner Purple and Jaipur Pink, pay homage to the architectural heritage of the respective cities.</li><li>The series features a quad-curve display, claimed to have the slimmest bezels in its segment.</li><li>It boasts a 50MP main camera with advanced image stabilization and innovative lighting features for superior low-light photography.</li><li>Equipped with AI Ultra Clarity 2.0 and the new AI Snap Mode for improved photography across various scenarios.</li></ul><blockquote>“With the MagicGlow Triple Flash system, users can enjoy enhanced illumination for vibrant low-light shots.”</blockquote><p>The realme 14 Pro Series 5G revolutionizes smartphone capabilities with cutting-edge technology and aesthetically pleasing design.</p>",
    "significance": [
      {
        "type": "Scale",
        "score": 8
      },
      {
        "type": "Impact",
        "score": 9
      },
      {
        "type": "Novelty",
        "score": 7
      },
      {
        "type": "Positivity",
        "score": 8
      },
      {
        "type": "Credibility",
        "score": 9
      },
      {
        "type": "Urgency",
        "score": 6
      },
      {
        "type": "Diversity of Impact",
        "score": 7
      },
      {
        "type": "Long-Term Significance",
        "score": 8
      },
      {
        "type": "Public Engagement",
        "score": 7
      },
      {
        "type": "Sentiment Intensity",
        "score": 5
      },
      {
        "type": "Geopolitical Significance",
        "score": 4
      },
      {
        "type": "Contextual Significance",
        "score": 6
      },
      {
        "type": "Economic Impact",
        "score": 8
      }
    ],
    "newTitle": "realme 14 Pro Series 5G Launching in India on January 16th"
  },
  {
    "title": "CES 2025: Samsung unveils AI-powered Neo QLED TVs, The Frame Pro, and more - Business Standard",
    "link": "https://www.business-standard.com/technology/tech-news/ces-2025-samsung-unveils-ai-powered-neo-qled-tvs-the-frame-pro-and-more-125010600271_1.html",
    "pubDate": "Mon, 06 Jan 2025 05:45:45 GMT",
    "summary": "<h1>Samsung Unveils AI-Powered Neo QLED TVs and Innovative Devices at CES 2025</h1><p><strong>Publication Date:</strong> Jan 06 2025 | <strong>Source:</strong> Business Standard</p><img src=\"https://www.business-standard.com/assets/web-assets/images/Business_Standard_685x385.jpg\" title=\"Samsung Neo QLED TV at CES 2025\" alt=\"Samsung Neo QLED TV at CES 2025\" width=\"826\" height=\"465\"><figcaption>Samsung Neo QLED TV at CES 2025</figcaption><p>At CES 2025 in Las Vegas, Samsung introduced a new lineup of AI-enhanced devices, including the Neo QLED TV, The Frame Pro, and a series of projectors, showcasing advancements in home entertainment technology.</p><ul><li>Samsung launched its 2025 TV line-up featuring new Neo QLED, OLED, and QLED models.</li><li>The flagship Neo QLED 8K QN990F TV employs Vision AI features for enhanced viewing experience.</li><li>The Frame Pro enhances artwork display quality while introducing new content from famous estates.</li><li>New interactive projector called The Premiere 5 with advanced features for user engagement.</li><li>Samsung's Ballie robots returned, with enhanced capabilities including a built-in projector.</li></ul><blockquote>“Samsung said that the new flagship TV model blends cutting-edge technology with an ultra-slim, minimalist design.”</blockquote><p>Samsung's innovations at CES 2025 highlight their commitment to integrating AI into consumer electronics, pushing the boundaries of how users experience home entertainment.</p>",
    "significance": [
      {
        "type": "Scale",
        "score": 8
      },
      {
        "type": "Impact",
        "score": 9
      },
      {
        "type": "Novelty",
        "score": 7
      },
      {
        "type": "Positivity",
        "score": 6
      },
      {
        "type": "Credibility",
        "score": 9
      },
      {
        "type": "Urgency",
        "score": 5
      },
      {
        "type": "Diversity of Impact",
        "score": 7
      },
      {
        "type": "Long-Term Significance",
        "score": 8
      },
      {
        "type": "Public Engagement",
        "score": 6
      },
      {
        "type": "Sentiment Intensity",
        "score": 5
      },
      {
        "type": "Geopolitical Significance",
        "score": 4
      },
      {
        "type": "Contextual Significance",
        "score": 6
      },
      {
        "type": "Economic Impact",
        "score": 8
      }
    ],
    "newTitle": "Samsung Unveils AI-Powered Neo QLED TVs and Innovative Devices at CES 2025"
  },
  {
    "title": "iPhone 17 Air price details leaked, will cost less than Pro models - India Today",
    "link": "https://www.indiatoday.in/technology/news/story/iphone-17-air-price-details-leaked-will-cost-less-than-pro-models-2660231-2025-01-06",
    "pubDate": "Mon, 06 Jan 2025 05:42:13 GMT",
    "summary": "<h1>The iPhone 17 Air Price Details Leaked</h1>\n<p><strong>Published On:</strong> Jan 6, 2025<br><strong>Source:</strong> Aman Rashid</p>\n<div><img fetchpriority=\"high\" src=\"https://akm-img-a-in.tosshub.com/indiatoday/images/story/202501/iphone-17-air-concept-source-frontpagetech-012244196-16x9.png?VersionId=hTb600SmlpqZ9n1fRmiWsQNHW6XVr5YL&amp;size=690:388\" width=\"690\" alt=\"iPhone 17 Air Concept/ Source: FrontPageTech\" title=\"iPhone 17 Air Concept/ Source: FrontPageTech\" height=\"388\">\n<figcaption>iPhone 17 Air Concept/ Source: FrontPageTech</figcaption></div>\n<p>Apple is gearing up to launch the iPhone 17 Air, touted to be the thinnest iPhone ever at just 6.25mm thick, featuring a 6.6-inch display and a single rear camera, targeting a similar price point to the iPhone 16 Plus.</p>\n<ul>\n  <li>The iPhone 17 Air is expected to be launched in September 2025.</li>\n  <li>It may be about 20% thinner than the iPhone 16 models, and around 25% thinner than the Pro models.</li>\n  <li>Pricing is expected to be around $899 in the USA, with similar pricing in the UK and India yet to be announced.</li>\n  <li>It will feature Apple’s new A19 chip, Dynamic Island, and 8GB of RAM.</li>\n  <li>The ultra-thin profile may lead to compromises like a smaller battery and reduced camera capabilities.</li>\n</ul>\n<blockquote>“A thinner phone often means a smaller battery, and with a single rear camera, photography enthusiasts might find themselves drawn to the Pro models instead.”</blockquote>\n<p>The iPhone 17 Air promises an exciting design with its ultra-slim profile, appealing to users looking for a lightweight device, though it raises questions about the trade-offs in features.</p>",
    "significance": [
      {
        "type": "Scale",
        "score": 8
      },
      {
        "type": "Impact",
        "score": 7
      },
      {
        "type": "Novelty",
        "score": 6
      },
      {
        "type": "Positivity",
        "score": 8
      },
      {
        "type": "Credibility",
        "score": 9
      },
      {
        "type": "Urgency",
        "score": 5
      },
      {
        "type": "Diversity of Impact",
        "score": 6
      },
      {
        "type": "Long-Term Significance",
        "score": 7
      },
      {
        "type": "Public Engagement",
        "score": 7
      },
      {
        "type": "Sentiment Intensity",
        "score": 6
      },
      {
        "type": "Geopolitical Significance",
        "score": 5
      },
      {
        "type": "Contextual Significance",
        "score": 4
      },
      {
        "type": "Economic Impact",
        "score": 6
      }
    ],
    "newTitle": "iPhone 17 Air Price Details Leaked, Will Cost Less Than Pro Models"
  },
  {
    "title": "WhatsApp rolling out document scanning feature - The Hindu",
    "link": "https://www.thehindu.com/sci-tech/technology/whatsapp-rolling-out-document-scanning-feature/article69067016.ece",
    "pubDate": "Mon, 06 Jan 2025 05:42:00 GMT",
    "summary": "<h1>WhatsApp rolling out document scanning feature</h1><p><strong>Date:</strong> January 06, 2025 <strong>Source:</strong> The Hindu</p><img src=\"https://th-i.thgim.com/public/incoming/me1777/article69067015.ece/alternates/LANDSCAPE_1200/IMG_FILE_PHOTO__Men_pose_2_1_OFDN31UK.jpg\" alt=\"iOS users reported they were able to use the document scanning feature [File]\" title=\"iOS users reported they were able to use the document scanning feature [File]\"><figcaption>Photo Credit: REUTERS</figcaption><p>Meta’s messaging service WhatsApp has launched a new document scanning feature, allowing users to scan documents they wish to send directly within the app, simplifying the process compared to previous methods.</p><ul><li>Users can now select the new 'Scan document' option when uploading documents to WhatsApp.</li><li>The feature improves the quality of scanned documents, producing brighter and clearer images compared to photos taken with a camera.</li><li>The update is currently available for some iOS users in India but is not yet rolled out to all Android and WhatsApp Business users.</li></ul><blockquote>Scanning a document results in a brighter and cleaner image where text and signatures are more legible.</blockquote><p>This new feature streamlines the document-sharing process on WhatsApp, enhancing user experience.</p>",
    "significance": [
      {
        "type": "Scale",
        "score": 7
      },
      {
        "type": "Impact",
        "score": 6
      },
      {
        "type": "Novelty",
        "score": 5
      },
      {
        "type": "Positivity",
        "score": 8
      },
      {
        "type": "Credibility",
        "score": 9
      },
      {
        "type": "Urgency",
        "score": 4
      },
      {
        "type": "Diversity of Impact",
        "score": 6
      },
      {
        "type": "Long-Term Significance",
        "score": 7
      },
      {
        "type": "Public Engagement",
        "score": 7
      },
      {
        "type": "Sentiment Intensity",
        "score": 5
      },
      {
        "type": "Geopolitical Significance",
        "score": 4
      },
      {
        "type": "Contextual Significance",
        "score": 6
      },
      {
        "type": "Economic Impact",
        "score": 5
      }
    ],
    "newTitle": "WhatsApp Introduces Document Scanning Feature for iOS Users"
  },
  {
    "title": "Samsung Galaxy S25 Ultra, Galaxy S25 Plus, Galaxy S25 Launch Date, Price, How To Watch Unpacked 2025 Live, All - Times Now",
    "link": "https://www.timesnownews.com/technology-science/gadgets/samsung-galaxy-s25-ultra-galaxy-s25-plus-galaxy-s25-launch-date-price-how-to-watch-unpacked-2025-live-all-you-need-to-know-article-116981589",
    "pubDate": "Mon, 06 Jan 2025 04:53:48 GMT",
    "summary": "<h1>Samsung Galaxy S25 Ultra, Galaxy S25 Plus, Galaxy S25 Launch Date, Price, How To Watch Unpacked 2025 Live, All</h1>\n<p><strong>Publication Date:</strong> January 12, 2025 &nbsp; <strong>Source:</strong> TNN</p>\n<img loading=\"lazy\" src=\"https://static.tnn.in/thumb/msid-116981591,thumbsize-1993312,width-1280,height-720,resizemode-75/116981591.jpg\" alt=\"Samsung Galaxy S25\" title=\"Samsung Galaxy S25\">\n<figcaption>Samsung Galaxy S25</figcaption>\n<p>Samsung's Galaxy S25 series will debut at the Galaxy Unpacked 2025 event, expected on January 22.</p>\n<ul>\n  <li>The Galaxy Unpacked event will unveil the Galaxy S25 series, featuring Galaxy S25, S25 Plus, and S25 Ultra.</li>\n  <li>The devices will include new designs, performance upgrades, and advanced AI features.</li>\n  <li>Expected specs include Snapdragon 8 Elite chipset and Android 15 with One UI 7.1.</li>\n  <li>Galaxy S25 Ultra rumored to have a 200MP main camera and advanced zoom capabilities.</li>\n  <li>Pricing may start at Rs 79,999 for Galaxy S25 and go up to Rs 1,29,999 for S25 Ultra.</li>\n  <li>A new model, Galaxy S25 Slim, may also be introduced with a thinner profile.</li>\n  <li>The event will be streamed live on Samsung's website and YouTube on January 22.</li>\n</ul>\n<blockquote>“The Galaxy S25 Ultra is rumored to feature a 200MP main camera, a 50MP ultra-wide lens, and advanced zoom capabilities.”</blockquote>\n<p>This upcoming launch showcases Samsung's commitment to advancing smartphone technology with new features and specifications.</p>",
    "significance": [
      {
        "type": "Scale",
        "score": 8
      },
      {
        "type": "Impact",
        "score": 9
      },
      {
        "type": "Novelty",
        "score": 7
      },
      {
        "type": "Positivity",
        "score": 8
      },
      {
        "type": "Credibility",
        "score": 10
      },
      {
        "type": "Urgency",
        "score": 5
      },
      {
        "type": "Diversity of Impact",
        "score": 6
      },
      {
        "type": "Long-Term Significance",
        "score": 8
      },
      {
        "type": "Public Engagement",
        "score": 9
      },
      {
        "type": "Sentiment Intensity",
        "score": 7
      },
      {
        "type": "Geopolitical Significance",
        "score": 5
      },
      {
        "type": "Contextual Significance",
        "score": 6
      },
      {
        "type": "Economic Impact",
        "score": 8
      }
    ],
    "newTitle": "Samsung Galaxy S25 Series Launch: Everything You Need to Know"
  },
  {
    "title": "Nothing Phone 2a Plus Gets Android 15 Update With AI-Powered Smart Drawer, New Customisations - Gadgets 360",
    "link": "https://www.gadgets360.com/mobiles/news/nothing-phone-2a-plus-os-3-android-15-update-release-features-7408785",
    "pubDate": "Mon, 06 Jan 2025 04:48:39 GMT",
    "summary": "<h1>Nothing Phone 2a Plus Users Can Now Experience Android 15 With New Update</h1>\n<p><strong>Publication Date:</strong> Not specified <strong>Source:</strong> Gadgets 360</p>\n<img src=\"https://img.youtube.com/vi/rE84dndRLec/hqdefault.jpg\" alt=\"Play Video\">\n<figcaption>Watch the update video</figcaption>\n<p>The latest update for Nothing Phone 2a Plus introduces Nothing OS 3.0, based on Android 15, offering new features and customisation options.</p>\n<ul>\n  <li>AI-powered smart drawer for app categorisation.</li>\n  <li>Enhanced lock screen customisation options.</li>\n  <li>Auto-archive functionality to free up storage.</li>\n  <li>Improved multi-tasking with draggable pop-up windows.</li>\n  <li>Shared Widgets feature for family and friends' widgets display.</li>\n  <li>Updated setup wizard and security patch from December 2024.</li>\n</ul>\n<blockquote>“Google's Circle to Search feature will be available post-update, leveraging AI for visual lookups.”</blockquote>\n<p>This update enhances user experience with AI features, customisation improvements, and multitasking capabilities, making it a significant upgrade for users of the Nothing Phone 2a Plus.</p>",
    "significance": [
      {
        "type": "Scale",
        "score": 5
      },
      {
        "type": "Impact",
        "score": 7
      },
      {
        "type": "Novelty",
        "score": 6
      },
      {
        "type": "Positivity",
        "score": 8
      },
      {
        "type": "Credibility",
        "score": 9
      },
      {
        "type": "Urgency",
        "score": 4
      },
      {
        "type": "Diversity of Impact",
        "score": 5
      },
      {
        "type": "Long-Term Significance",
        "score": 6
      },
      {
        "type": "Public Engagement",
        "score": 7
      },
      {
        "type": "Sentiment Intensity",
        "score": 5
      },
      {
        "type": "Geopolitical Significance",
        "score": 3
      },
      {
        "type": "Contextual Significance",
        "score": 4
      },
      {
        "type": "Economic Impact",
        "score": 6
      }
    ],
    "newTitle": "Nothing Phone 2a Plus Users Can Now Experience Android 15 With New Update"
  },
  {
    "title": "Oppo Reno 13 series price leaked ahead of its launch on January 9 - India Today",
    "link": "https://www.indiatoday.in/technology/news/story/oppo-reno-13-series-price-leaked-ahead-of-its-launch-on-january-9-2660195-2025-01-06",
    "pubDate": "Mon, 06 Jan 2025 04:44:48 GMT",
    "summary": "<h1>Oppo Reno 13 Series Pricing Leaked Ahead of January 9 Launch</h1><p><strong>Published On:</strong> Jan 6, 2025 <strong>Source:</strong> Unnati Gusain</p><h3>Introduction</h3><p>The Oppo Reno 13 series, set to launch in India on January 9, has had its prices leaked ahead of time, revealing details about the upcoming models.</p><h3>Key Points</h3><ul><li>The series includes two variants: the Reno 13 and Reno 13 Pro.</li><li>Prices start at Rs 37,999 for the Reno 13 with 8GB RAM and 128GB storage.</li><li>The Pro model is expected to be priced at Rs 49,999 for the 12GB RAM and 256GB storage variant.</li><li>Specifications include a MediaTek Dimensity 8350 chipset and AI camera features.</li><li>Battery capacities are 5,600mAh for the standard model and 5,800mAh for the Pro model.</li><li>The design focuses on durability with a premium aluminum frame and Corning Gorilla Glass 7i.</li></ul><h3>Notable Quotes or Statistics</h3><blockquote>“The teaser visuals reveal that the Reno 13 series 5G will include a flat display and a triple-camera setup.”</blockquote><h3>Conclusion</h3><p>Details are expected to be officially confirmed during the January 9 launch, including potential discounts on the listed prices.</p>",
    "significance": [
      {
        "type": "Scale",
        "score": 7
      },
      {
        "type": "Impact",
        "score": 6
      },
      {
        "type": "Novelty",
        "score": 5
      },
      {
        "type": "Positivity",
        "score": 8
      },
      {
        "type": "Credibility",
        "score": 9
      },
      {
        "type": "Urgency",
        "score": 4
      },
      {
        "type": "Diversity of Impact",
        "score": 6
      },
      {
        "type": "Long-Term Significance",
        "score": 5
      },
      {
        "type": "Public Engagement",
        "score": 7
      },
      {
        "type": "Sentiment Intensity",
        "score": 5
      },
      {
        "type": "Geopolitical Significance",
        "score": 6
      },
      {
        "type": "Contextual Significance",
        "score": 6
      },
      {
        "type": "Economic Impact"
      }
    ],
    "newTitle": "Oppo Reno 13 Series Pricing Leaked Ahead of January 9 Launch"
  },
  {
    "title": "Apple iPhone SE 4: Disappointing News For iPhone Lovers! Upcoming Smartphone To Be More Expensive, REVEALS Report - News24",
    "link": "https://news24online.com/tech/apple-iphone-se-4-disappointing-news-for-iphone-lovers-upcoming-smartphone-to-be-more-expensive-reveals-report/432318/",
    "pubDate": "Mon, 06 Jan 2025 04:31:59 GMT",
    "summary": "<h1>Apple iPhone SE 4: Disappointing News For iPhone Lovers!</h1>\n<p><strong>Date:</strong> Jan 06, 2025 <strong>Source:</strong> News24</p>\n<img loading=\"lazy\" decoding=\"async\" src=\"https://pbs.twimg.com/media/GffnM7TWAAAGmDh?format=jpg&amp;name=medium\" alt=\"Photo Credit: Apple Tech Way\" width=\"819\" height=\"1024\">\n<figcaption>Photo Credit: Apple Tech Way</figcaption>\n<p>Anticipation for the iPhone SE 4 has surged, but new reports suggest it may come with a higher price tag than expected.</p>\n<ul>\n  <li>The iPhone SE 4 is rumored to debut at around KRW 8,00,000 (~INR 46,000 or $500), marking a price increase from the SE 3.</li>\n  <li>Expected design improvements include a 6.1-inch OLED display, potentially inspired by the iPhone 14, featuring Face ID.</li>\n  <li>Equipped with Apple’s new A18 chip and up to 8GB of RAM for enhanced performance.</li>\n  <li>Will include Apple’s first in-house 5G modem, marking a technological shift for the company.</li>\n  <li>Questions remain about whether the price will stay under INR 50,000, which would make it highly competitive in the Indian market.</li>\n</ul>\n<blockquote>“Apple’s gamble to blend affordability with innovative technology might just tap into the aspirations of millions.”</blockquote>\n<p>The iPhone SE 4 is set to capture attention with its blend of premium features at a new price point, raising questions on its value to consumers.</p>",
    "significance": [
      {
        "type": "Scale",
        "score": 7
      },
      {
        "type": "Impact",
        "score": 6
      },
      {
        "type": "Novelty",
        "score": 5
      },
      {
        "type": "Positivity",
        "score": 4
      },
      {
        "type": "Credibility",
        "score": 8
      },
      {
        "type": "Urgency",
        "score": 5
      },
      {
        "type": "Diversity of Impact",
        "score": 6
      },
      {
        "type": "Long-Term Significance",
        "score": 7
      },
      {
        "type": "Public Engagement",
        "score": 8
      },
      {
        "type": "Sentiment Intensity",
        "score": 4
      },
      {
        "type": "Geopolitical Significance",
        "score": 5
      },
      {
        "type": "Contextual Significance",
        "score": 7
      },
      {
        "type": "Economic Impact",
        "score": 6
      }
    ],
    "newTitle": "Apple iPhone SE 4: Disappointing News For iPhone Lovers!"
  },
  {
    "title": "Belkin Boosts CES 2025 Lineup With New Audio Concepts, Content Creator Tools, and Premium Charging Solutions Made With Up to 90% Recycled Materials - Business Wire India",
    "link": "https://www.businesswireindia.com/belkin-boosts-ces-2025-lineup-with-new-audio-concepts-content-creator-tools-and-premium-charging-solutions-made-with-up-to-90percent-recycled-materials-93027.html",
    "pubDate": "Mon, 06 Jan 2025 04:30:40 GMT",
    "summary": "<h1>Belkin Boosts CES 2025 Lineup With New Audio Concepts, Content Creator Tools, and Premium Charging Solutions Made With Up to 90% Recycled Materials</h1><p><strong>Publication Date:</strong> January 5, 2025</p><p><strong>Source:</strong> Business Wire</p><img src=\"https://mms.businesswire.com/media/20250105036719/en/2338981/4/CES_2025_lockup.jpg\" alt=\"Belkin Announces New Products at CES 2025 (Photo: Business Wire)\"><figcaption>Belkin Announces New Products at CES 2025 (Photo: Business Wire)</figcaption><p>Belkin has introduced new products at CES Unveiled Las Vegas, highlighting its commitment to quality and sustainability by utilizing up to 90% recycled materials in their new lineup.</p><ul><li>Belkin has transitioned over 359 products to use 72-75% post-consumer recycled materials.</li><li>New accessories will feature 85-90% post-consumer recycled materials starting in Q2 2025.</li><li>Highlighted products include the BoostCharge Pro Magnetic Wireless Charging Pad and BoostCharge Power Bank.</li><li>Belkin aims for 100% carbon neutrality in operations by 2025 and across its business by 2030.</li></ul><blockquote>“This initiative is estimated to reduce CO2-eq emissions for these product materials by up to 84.8%.”</blockquote><p>The launch at CES 2025 demonstrates Belkin's innovative approach to sustainable technology.</p>",
    "significance": [
      {
        "type": "Scale",
        "score": 8
      },
      {
        "type": "Impact",
        "score": 7
      },
      {
        "type": "Novelty",
        "score": 9
      },
      {
        "type": "Positivity",
        "score": 6
      },
      {
        "type": "Credibility",
        "score": 9
      },
      {
        "type": "Urgency",
        "score": 5
      },
      {
        "type": "Diversity of Impact",
        "score": 8
      },
      {
        "type": "Long-Term Significance",
        "score": 7
      },
      {
        "type": "Public Engagement",
        "score": 8
      },
      {
        "type": "Sentiment Intensity",
        "score": 6
      },
      {
        "type": "Geopolitical Significance",
        "score": 7
      },
      {
        "type": "Contextual Significance",
        "score": 8
      },
      {
        "type": "Economic Impact",
        "score": 8
      }
    ],
    "newTitle": "Belkin Unveils New Eco-Friendly Products at CES 2025"
  },
  {
    "title": "Oppo Reno 13, Reno 13 Pro India launch date confirmed- Know what’s coming - HT Tech",
    "link": "https://news.google.com/rss/articles/CBMi0AFBVV95cUxNRFdtZ1dJd3pCRE9WbmxoZEwxS0dfMUdQSUJYVW5hU1lpZ2wwUVhSS3BZSXg0bndyZWVPMkdxMXJzY2hWNUZNWjg1MEFIeW01RkQxWHZUZHlPVTJIODNhR3pPdTBNWFhVUGFrT1Nka2ZxZEVYNTRmdUJrazNuOWpfckxMejc5bm9uT2hvTW9UbDBkN0ZaV0I2X3RBTlF2QUVFbVp3T1lFVTFYUmFWdzBHV09uVXFOdS1vd0RyZUJ3TGFMTUJpclJVekZtWGdtN2dt0gHWAUFVX3lxTE5IckRhajk0T1VGaW9YTG9uVElCbkt4NmpKaHVtSnhrUTVueVBrMUtUZF8xNHZSdG9GRF9HSjc0aEVUNTFoalozQnhyZGNCVXI1bTZlRmNMYkhOdDJOa1dvcjhqNlJSY19kd1NjM2tvajM0LTNJX3AyYVltQjdKZzFGUHB2dGFwWGZaYTYtS25yZGt6S05kVGliRXBLV0JaTkdEMnVub0FmbFMwRjhSQnRiOFlBV05JdmpIVHl1Qi1VNGxRMWZUS1lIamIwUkJlTnZOQWtxaFE?oc=5&hl=en-US&gl=US&ceid=US:en",
    "pubDate": "Mon, 06 Jan 2025 04:26:55 GMT",
    "summary": null,
    "significance": null,
    "newTitle": null
  },
  {
    "title": "Garena Free Fire MAX redeem codes for January 6: Win diamonds, pets, skins, and more - The Times of India",
    "link": "https://timesofindia.indiatimes.com/technology/gaming/garena-free-fire-max-redeem-codes-for-january-6-win-diamonds-pets-skins-and-more/articleshow/116980329.cms",
    "pubDate": "Mon, 06 Jan 2025 04:21:00 GMT",
    "summary": "<h1>Garena Free Fire MAX Redeem Codes for January 6: Win Diamonds, Pets, Skins, and More</h1><p><strong>Date:</strong> January 6, 2023 <strong>Source:</strong> Garena News</p><p>This article provides the latest redeem codes for Garena Free Fire MAX, offering players opportunities to win exclusive in-game items such as diamonds, pets, and various skins.</p><ul><li>Players can enter redeem codes to unlock rewards.</li><li>Rewards include diamonds, pets, and character skins.</li><li>The article lists several active redeem codes valid for use.</li></ul><blockquote>“Participating in events and using redeem codes is a great way to enhance your gaming experience in Free Fire!”</blockquote><p>In conclusion, players are encouraged to take advantage of these redeem codes while they last to upgrade their gameplay and collect exciting rewards.</p>",
    "significance": [
      {
        "type": "Scale",
        "score": 8
      },
      {
        "type": "Impact",
        "score": 7
      },
      {
        "type": "Novelty",
        "score": 6
      },
      {
        "type": "Positivity",
        "score": 9
      },
      {
        "type": "Credibility",
        "score": 8
      },
      {
        "type": "Urgency",
        "score": 5
      },
      {
        "type": "Diversity of Impact",
        "score": 7
      },
      {
        "type": "Long-Term Significance",
        "score": 6
      },
      {
        "type": "Public Engagement",
        "score": 7
      },
      {
        "type": "Sentiment Intensity",
        "score": 5
      },
      {
        "type": "Geopolitical Significance",
        "score": 4
      },
      {
        "type": "Contextual Significance",
        "score": 6
      },
      {
        "type": "Economic Impact",
        "score": 5
      }
    ],
    "newTitle": "Garena Free Fire MAX Redeem Codes for January 6: Win Diamonds, Pets, Skins, and More"
  },
  {
    "title": "OnePlus 13, OnePlus 13R launching tomorrow: What to expect? - India Today",
    "link": "https://www.indiatoday.in/technology/news/story/oneplus-13-oneplus-13r-launching-tomorrow-what-to-expect-2660208-2025-01-06",
    "pubDate": "Mon, 06 Jan 2025 04:20:44 GMT",
    "summary": "<h1>OnePlus 13, OnePlus 13R launching tomorrow: What to expect?</h1><p><strong>Published On:</strong> Jan 6, 2025 &nbsp; | &nbsp; <strong>Source:</strong> Aman Rashid</p><div><img fetchpriority=\"high\" src=\"https://akm-img-a-in.tosshub.com/indiatoday/images/story/202501/oneplus-13-022735662-16x9_0.png?VersionId=yCns_7dOf.XsgH55mIioy5tv4Lxn.224&amp;size=690:388\" width=\"690\" alt=\"OnePlus 13\" title=\"OnePlus 13 will now come in two finishes — vegan leather and glass.\" height=\"388\"><figcaption>OnePlus 13 will now come in two finishes — vegan leather and glass.</figcaption></div><p>OnePlus is all set to launch its highly awaited OnePlus 13 and OnePlus 13R on January 7. With only a day left before the big event, the company has revealed a few details about the features and upgrades these new devices will bring.</p><ul><li>The OnePlus 13 is expected to cost under Rs 70,000 for its base variant.</li><li>The OnePlus 13R is likely to launch at under Rs 50,000.</li><li>Both models will have flat sides with a clean and minimalistic design.</li><li>Both devices will feature a 6,000mAh battery with fast charging support.</li><li>The OnePlus 13 will be powered by the Snapdragon 8 Elite chipset, while the 13R will have the Snapdragon 8 Gen 3 chipset.</li><li>Camera specs include advanced lenses and sensors, with the 13R marking the first R-series device to include a telephoto lens.</li></ul><blockquote>“The OnePlus 13 is expected to receive 4 years of Android updates and 5 years of security patches, while the OnePlus 13R may get 3 years of Android updates and 4 years of security patches.”</blockquote><p>This launch marks significant advancements for OnePlus, with better design, performance, and features catering to different segments of the market.</p>",
    "significance": [
      {
        "type": "Scale",
        "score": 8
      },
      {
        "type": "Impact",
        "score": 7
      },
      {
        "type": "Novelty",
        "score": 6
      },
      {
        "type": "Positivity",
        "score": 5
      },
      {
        "type": "Credibility",
        "score": 9
      },
      {
        "type": "Urgency",
        "score": 4
      },
      {
        "type": "Diversity of Impact",
        "score": 7
      },
      {
        "type": "Long-Term Significance",
        "score": 6
      },
      {
        "type": "Public Engagement",
        "score": 8
      },
      {
        "type": "Sentiment Intensity",
        "score": 6
      },
      {
        "type": "Geopolitical Significance",
        "score": 5
      },
      {
        "type": "Contextual Significance",
        "score": 7
      },
      {
        "type": "Economic Impact",
        "score": 4
      }
    ],
    "newTitle": "OnePlus 13 and 13R Launching Tomorrow: Key Details and Expectations"
  },
  {
    "title": "Redmi 14C 5G to launch in India today: Specs, price, and how to watch the event - The Financial Express",
    "link": "https://www.financialexpress.com/life/technology-redmi-14c-5g-to-launch-in-india-today-specs-price-and-how-to-watch-the-event-3707927/",
    "pubDate": "Mon, 06 Jan 2025 04:07:35 GMT",
    "summary": "<h1>Xiaomi Launches Redmi 14C 5G in India Today</h1><p><strong>Date:</strong> January 6, 2025<br><strong>Source:</strong> Financial Express</p><h2>Introduction</h2><p>Xiaomi is set to launch the Redmi 14C 5G in India today, marking the first major smartphone release of 2025 and aiming to provide affordable 5G connectivity.</p><h2>Key Points</h2><ul><li>The launch event will be streamed live at 12 noon on Xiaomi India's official YouTube channel.</li><li>Redmi 14C 5G features a 6.88-inch display with a 120Hz refresh rate and is powered by the Snapdragon 4 Gen 2 processor.</li><li>It includes a 50-megapixel primary camera and supports 5G dual SIM.</li><li>The expected price is under Rs 15,000, continuing Xiaomi's commitment to budget-friendly devices.</li><li>Xiaomi has additional launches planned this month, including the Xiaomi Pad 7 on January 10.</li></ul><h2>Notable Quotes or Statistics</h2><blockquote>\"Xiaomi aims to keep providing budget-friendly 5G smartphones, following the success of the Redmi 13C 5G at Rs 10,999.\"</blockquote><h2>Conclusion</h2><p>The Redmi 14C 5G's launch is significant for budget-conscious consumers looking for affordable 5G options in India, setting the tone for an active month for Xiaomi.</p>",
    "significance": [
      {
        "type": "Scale",
        "score": 8
      },
      {
        "type": "Impact",
        "score": 7
      },
      {
        "type": "Novelty",
        "score": 6
      },
      {
        "type": "Positivity",
        "score": 9
      },
      {
        "type": "Credibility",
        "score": 8
      },
      {
        "type": "Urgency",
        "score": 5
      },
      {
        "type": "Diversity of Impact",
        "score": 7
      },
      {
        "type": "Long-Term Significance",
        "score": 8
      },
      {
        "type": "Public Engagement",
        "score": 6
      },
      {
        "type": "Sentiment Intensity",
        "score": 7
      },
      {
        "type": "Geopolitical Significance",
        "score": 5
      },
      {
        "type": "Contextual Significance",
        "score": 6
      },
      {
        "type": "Economic Impact",
        "score": 7
      }
    ],
    "newTitle": "Xiaomi Launches Redmi 14C 5G in India Today"
  },
  {
    "title": "Garena Free Fire MAX redeem codes for January 6, 2025: Claim free diamonds, weapons, skins, and rewards - Indiatimes.com",
    "link": "https://news.google.com/rss/articles/CBMi3AFBVV95cUxPMG9DN2VMd09CSDNQYWJMcVJyMnBQeXJabVIxS1ROMTFZdTVzVTBwenhaWkhXQ2k1endZQVYxUHNySUJSQUJzcWJ3aHFrZXYxNGYtcWtxaHRoOHNoS2JvVWRERHhLU3B4bkJReGJ4Zlpjeml0QlM4cUFzRHRQaE9hSWRyamlRc3NBblBLYUtQelRCMlpBV25CMGpSSnQwbURfWXRyN3JfZ1RrS2liSlZOWDI0VXpBb3BzbXN3SThYNzcwSGh6UkdSR3FFQ1NzRURzLUVsU1JPOGRIMlFq0gHiAUFVX3lxTFBOTFhNa01kVG5HakhwVHo2NUd0YVkxU1FjazdzRF8wejF3bWpqY25RazFkNG9Oenh0LWpIcU8xQWlPZ0lacC1uREJLbXlCZmQwdmo0ZFBaM25ZbUs5bHA3b3dxLW1rZVJseEd2TlltUzFNams2ZW92VWZfdng4b2F6LVR0Nl9jYXlmM1hVSVZPSGdXSUFiRXJiNXRsVjRseXE0YTNBdVdPZ3lzQXJCSmpKd0FPa2xoakFZaEoyS0s0OTRGOG45SU9aUEU2VzdiQWdpekFZTm9HZHo2czlHZXlZalE?oc=5&hl=en-US&gl=US&ceid=US:en",
    "pubDate": "Mon, 06 Jan 2025 04:01:41 GMT",
    "summary": null,
    "significance": null,
    "newTitle": null
  },
  {
    "title": "Leaked Realme 14 Pro series poster reveals key specifications like processor, battery - 91mobiles",
    "link": "https://www.91mobiles.com/hub/leaked-realme-14-pro-series-specifications-revealed/",
    "pubDate": "Mon, 06 Jan 2025 03:51:02 GMT",
    "summary": "<h1>Leaked Realme 14 Pro series poster reveals key specifications like processor, battery</h1><p><strong>Publication Date:</strong> January 2025<br><strong>Source:</strong> 91mobiles</p><img src=\"https://www.91-cdn.com/hub/wp-content/uploads/2025/01/Realme-14-Pro-1.png?tr=w-781\" alt=\"Realme 14 Pro Series\"> <figcaption>Leaked image of the Realme 14 Pro series.</figcaption><p>The Realme 14 Pro series is set to launch in India soon, with details about its specifications and design gradually being revealed through leaks and teasers.</p><ul><li>Processor: The Realme 14 Pro is powered by the Dimensity 7300 chipset, outperforming the Snapdragon 7s Gen 2.</li><li>Battery: A 6,000mAh battery with 45W charging support, claimed to be the slimmest phone with such a capacity at 7.55mm.</li><li>Camera: Features a primary camera with Sony IMX882 and OIS, alongside a 16MP front camera.</li><li>Display: Offers a 120Hz curved display with a 1.5K resolution for a superior viewing experience.</li><li>Design: Includes IP66+IP68+IP69 ratings, military-grade durability, and a unique Pearl design.</li></ul><h2>Realme 14 Pro+ Specifications</h2><p>The Pro+ variant shares a similar design but features a Snapdragon 7s Gen 3 SoC and an edge-to-edge bezel-less quad-curve display.</p><blockquote><p>The Realme 14 Pro series is confirmed to launch in January 2025, with more details expected to follow.</p></blockquote><p>In summary, the Realme 14 Pro series boasts impressive specifications and innovative features, setting high expectations for its launch.</p>",
    "significance": [
      {
        "type": "Scale",
        "score": 8
      },
      {
        "type": "Impact",
        "score": 7
      },
      {
        "type": "Novelty",
        "score": 5
      },
      {
        "type": "Positivity",
        "score": 6
      },
      {
        "type": "Credibility",
        "score": 9
      },
      {
        "type": "Urgency",
        "score": 2
      },
      {
        "type": "Diversity of Impact",
        "score": 4
      },
      {
        "type": "Long-Term Significance",
        "score": 6
      },
      {
        "type": "Public Engagement",
        "score": 7
      },
      {
        "type": "Sentiment Intensity",
        "score": 3
      },
      {
        "type": "Geopolitical Significance",
        "score": 4
      },
      {
        "type": "Contextual Significance",
        "score": 5
      },
      {
        "type": "Economic Impact",
        "score": 6
      }
    ],
    "newTitle": "Leaked Details of the Upcoming Realme 14 Pro Series Unveiled"
  }
]