[
  {
    "title": "Brett Favre is asking an appeals court to reinstate his defamation lawsuit against Shannon Sharpe",
    "link": "https://www.yahoo.com/news/brett-favre-asking-appeals-court-040739951.html",
    "pubDate": "2024-07-09T04:07:39Z"
  },
  {
    "title": "Child held by one leg over Daytona hotel's second floor balcony, dropped head first",
    "link": "https://www.yahoo.com/news/child-held-one-leg-over-202209819.html",
    "pubDate": "2024-07-08T20:22:09Z"
  },
  {
    "title": "SLO County cyclist thought a mountain lion attacked him. Here’s what it actually was",
    "link": "https://www.yahoo.com/news/slo-county-cyclist-thought-mountain-221922824.html",
    "pubDate": "2024-07-09T22:19:22Z"
  },
  {
    "title": "FAA orders inspection of 2,600 Boeing 737s over oxygen mask issue",
    "link": "https://finance.yahoo.com/news/faa-orders-inspections-2-600-160215459.html",
    "pubDate": "2024-07-08T16:02:15Z"
  },
  {
    "title": "Petition launched in response to deadly crash involving Utah CEO, daughter in Ogden Canyon",
    "link": "https://www.yahoo.com/news/petition-launched-response-deadly-crash-011340312.html",
    "pubDate": "2024-07-09T01:13:40Z"
  },
  {
    "title": "Dozens of Chicago area Mariano's, Jewel-Osco stores to be sold in supermarket merger talks",
    "link": "https://finance.yahoo.com/news/dozens-chicago-area-marianos-jewel-213652882.html",
    "pubDate": "2024-07-09T21:36:52Z"
  },
  {
    "title": "Three Gazans found dead after release from Israeli custody, relative and witness say",
    "link": "https://www.yahoo.com/news/three-gazans-found-dead-release-102459774.html",
    "pubDate": "2024-07-08T10:24:59Z"
  },
  {
    "title": "New York Times, Politico, others criticized for 'offensive' obituaries on deceased former GOP senator",
    "link": "https://www.yahoo.com/news/york-times-politico-others-criticized-000034974.html",
    "pubDate": "2024-07-10T00:00:34Z"
  },
  {
    "title": "Does setting my AC to 78 degrees save money during California heat wave? What expert says",
    "link": "https://www.yahoo.com/news/does-setting-ac-78-degrees-130000205.html",
    "pubDate": "2024-07-09T13:00:00Z"
  },
  {
    "title": "Karen Read’s defense team says jurors were unanimous on acquitting her of murder",
    "link": "https://www.yahoo.com/news/karen-read-defense-team-says-172705153.html",
    "pubDate": "2024-07-08T17:27:05Z"
  },
  {
    "title": "ABC News’ George Stephanopoulous Backs Away From Remark on Biden’s White House Chances",
    "link": "https://www.yahoo.com/news/abc-news-george-stephanopoulos-apologizes-015548794.html",
    "pubDate": "2024-07-10T01:55:48Z"
  },
  {
    "title": "'Playing COVID roulette': Some infected by FLiRT variants report their most unpleasant symptoms yet",
    "link": "https://www.yahoo.com/news/playing-covid-roulette-infected-flirt-100026293.html",
    "pubDate": "2024-07-08T10:00:26Z"
  },
  {
    "title": "2024 Toyota Mirai gets a huge July promotion, up to $33,000 off MSRP",
    "link": "https://www.autoblog.com/2024/07/08/2024-toyota-mirai-gets-a-huge-july-promotion-up-to-33000-off-msrp/",
    "pubDate": "2024-07-08T12:07:00Z"
  },
  {
    "title": "Reporter: Trump’s dislike of facial feature could affect VP pick",
    "link": "https://www.yahoo.com/news/reporter-trump-dislike-facial-feature-010726768.html",
    "pubDate": "2024-07-09T01:07:26Z"
  },
  {
    "title": "He bought a cheap house in Italy to improve his life expectancy",
    "link": "https://www.yahoo.com/lifestyle/bought-cheap-house-italy-improve-101215697.html",
    "pubDate": "2024-07-09T10:12:15Z"
  },
  {
    "title": "Defence minister urges Ukrainians throughout Europe to join new legion",
    "link": "https://www.yahoo.com/news/defence-minister-urges-ukrainians-throughout-232403366.html",
    "pubDate": "2024-07-09T23:24:03Z"
  },
  {
    "title": "James Webb Space Telescope suggests this exoplanet is our 'best bet' at finding an alien ocean",
    "link": "https://www.yahoo.com/news/james-webb-space-telescope-suggests-192144678.html",
    "pubDate": "2024-07-08T19:21:44Z"
  },
  {
    "title": "McDonald’s Is Bringing Back a Fan-Favorite Burger for the First Time in 2 Years",
    "link": "https://www.yahoo.com/lifestyle/mcdonald-bringing-back-fan-favorite-210000847.html",
    "pubDate": "2024-07-08T21:00:00Z"
  },
  {
    "title": "EV maker Lucid beats quarterly deliveries estimates helped by price cuts",
    "link": "https://finance.yahoo.com/news/ev-maker-lucid-beats-quarterly-130347345.html",
    "pubDate": "2024-07-08T13:03:47Z"
  },
  {
    "title": "Woman, 19, arrested after deadly north Phoenix crash, PD says",
    "link": "https://www.yahoo.com/news/woman-19-arrested-deadly-north-040304948.html",
    "pubDate": "2024-07-09T04:03:04Z"
  },
  {
    "title": "Don’t ignore this one skin sign that might mean cancer, doctor warns",
    "link": "https://www.yahoo.com/news/don-t-ignore-one-skin-192005992.html",
    "pubDate": "2024-07-08T19:20:05Z"
  },
  {
    "title": "Public policy favors $7 billion fee award in Musk pay case, Tesla shareholder's lawyer says",
    "link": "https://finance.yahoo.com/news/tesla-investors-urge-judge-reject-100304056.html",
    "pubDate": "2024-07-08T10:03:04Z"
  },
  {
    "title": "Climbers in Malibu find abandoned German Shepherd with zip ties around mouth, neck",
    "link": "https://www.yahoo.com/news/climbers-malibu-abandoned-german-shepherd-135212154.html",
    "pubDate": "2024-07-09T13:52:12Z"
  },
  {
    "title": "Drone Footage Shows Swamped Roads in Houston After Beryl",
    "link": "https://www.yahoo.com/news/drone-footage-shows-swamped-roads-072909641.html",
    "pubDate": "2024-07-09T07:29:09Z"
  },
  {
    "title": "Iran's president-elect reaffirms policy towards Israel",
    "link": "https://www.yahoo.com/news/irans-president-elect-reaffirms-policy-162553758.html",
    "pubDate": "2024-07-08T16:25:53Z"
  },
  {
    "title": "Bitcoin Drops as German Government Unloads Over $900M Worth of BTC",
    "link": "https://finance.yahoo.com/news/bitcoin-drops-german-government-unloads-151312520.html",
    "pubDate": "2024-07-08T15:13:12Z"
  },
  {
    "title": "Earth's gravity knocked pyramid-size asteroid off course during recent ultra-close flyby, NASA images reveal",
    "link": "https://www.yahoo.com/news/earths-gravity-knocked-pyramid-size-170433281.html",
    "pubDate": "2024-07-09T17:04:33Z"
  },
  {
    "title": "Hunter Biden ends bid for gun retrial after prosecutors explain appeal process",
    "link": "https://www.yahoo.com/news/hunter-biden-withdraws-motion-trial-150221582.html",
    "pubDate": "2024-07-09T15:02:21Z"
  },
  {
    "title": "\"I just remember the claws digging into my back\" – runner recovering after hair clip saves her during grizzly bear attack",
    "link": "https://www.yahoo.com/news/just-remember-claws-digging-back-084916062.html",
    "pubDate": "2024-07-09T08:49:16Z"
  },
  {
    "title": "New cyberattack targets iPhone Apple IDs. Here's how to protect yourself.",
    "link": "https://www.yahoo.com/tech/cyberattack-targets-iphone-apple-ids-191000974.html",
    "pubDate": "2024-07-08T19:10:00Z"
  },
  {
    "title": "ASML CEO says world needs the legacy chips China is producing, Handelsblatt reports",
    "link": "https://finance.yahoo.com/news/asml-ceo-says-world-needs-100835456.html",
    "pubDate": "2024-07-08T10:08:35Z"
  },
  {
    "title": "Two Boise fires, three houses damaged, one cause: The improper disposal of fireworks",
    "link": "https://www.yahoo.com/news/two-boise-fires-three-houses-193027794.html",
    "pubDate": "2024-07-08T19:30:27Z"
  },
  {
    "title": "Photos show the mysterious ancient objects that mountaineers are finding on the Alps' melting glaciers",
    "link": "https://www.yahoo.com/tech/photos-show-mysterious-ancient-objects-151617346.html",
    "pubDate": "2024-07-09T15:16:17Z"
  },
  {
    "title": "Cuba foils plot to sneak arms onto island from U.S., official says",
    "link": "https://www.yahoo.com/news/cuba-foils-plot-sneak-arms-231623993.html",
    "pubDate": "2024-07-08T23:16:23Z"
  },
  {
    "title": "Chase’s plan to charge for checking accounts—and how consumers might respond",
    "link": "https://finance.yahoo.com/news/chase-plan-charge-checking-accounts-192830672.html",
    "pubDate": "2024-07-08T19:28:30Z"
  },
  {
    "title": "University of Florida suspends arrested pro-Palestinian protesters for up to 4 years",
    "link": "https://www.yahoo.com/news/university-florida-suspends-arrested-pro-181001126.html",
    "pubDate": "2024-07-09T18:10:01Z"
  },
  {
    "title": "A woman who received a pig kidney transplant plus a heart pump has died",
    "link": "https://www.yahoo.com/news/woman-received-pig-kidney-transplant-154745318.html",
    "pubDate": "2024-07-09T15:47:45Z"
  },
  {
    "title": "Body of American climber who died 22 years ago found on Peru's highest summit",
    "link": "https://www.yahoo.com/news/body-american-climber-died-22-160724675.html",
    "pubDate": "2024-07-09T16:07:24Z"
  },
  {
    "title": "Want to Prevent Heart Disease? A Huge Study Says This Is the Exact Blood Pressure You Should Aim For",
    "link": "https://www.yahoo.com/news/want-prevent-heart-disease-huge-102500758.html",
    "pubDate": "2024-07-09T10:25:00Z"
  },
  {
    "title": "The unemployment rate is just 0.1% from causing a major headache for the Fed: Morning Brief",
    "link": "https://finance.yahoo.com/news/the-unemployment-rate-is-just-01-from-causing-a-major-headache-for-the-fed-morning-brief-100050811.html",
    "pubDate": "2024-07-09T10:00:50Z"
  },
  {
    "title": "10 Signs You’ll Retire Comfortably in the Middle Class",
    "link": "https://finance.yahoo.com/news/10-signs-ll-retire-comfortably-160020141.html",
    "pubDate": "2024-07-08T15:01:01Z"
  },
  {
    "title": "Church's Chicken employee killed after argument with drive-thru customer; no arrest made",
    "link": "https://www.yahoo.com/news/churchs-chicken-employee-killed-argument-153639479.html",
    "pubDate": "2024-07-09T15:36:39Z"
  },
  {
    "title": "Tehran police close Turkish Airlines office after its employees defy Iran's headscarf law",
    "link": "https://www.yahoo.com/news/tehran-police-close-turkish-airlines-181930133.html",
    "pubDate": "2024-07-09T18:19:30Z"
  },
  {
    "title": "What the polls show 11 days after the Biden-Trump debate",
    "link": "https://www.yahoo.com/news/polls-show-11-days-biden-234839618.html",
    "pubDate": "2024-07-08T23:48:39Z"
  },
  {
    "title": "Chinese EV makers pivot to the Global South to survive Western tariffs",
    "link": "https://finance.yahoo.com/news/chinese-ev-makers-pivot-global-185403897.html",
    "pubDate": "2024-07-08T18:54:03Z"
  },
  {
    "title": "Japan Navy helicopters' fatal crash caused by inadequate instructions to crew, says probe report",
    "link": "https://www.yahoo.com/news/japan-navy-helicopters-fatal-crash-142603164.html",
    "pubDate": "2024-07-09T14:26:03Z"
  },
  {
    "title": "Ford, Toyota, General Motors among 57,000 vehicles recalled: Check car recalls here",
    "link": "https://www.yahoo.com/news/ford-toyota-general-motors-among-104035395.html",
    "pubDate": "2024-07-08T10:40:35Z"
  },
  {
    "title": "MrBeast Arrested: What Happened to the YouTuber in 2023?",
    "link": "https://www.yahoo.com/entertainment/mrbeast-arrested-happened-youtuber-2023-100853850.html",
    "pubDate": "2024-07-08T10:08:53Z"
  },
  {
    "title": "US economy no longer overheated, Fed's Powell tells Congress",
    "link": "https://finance.yahoo.com/news/feds-powell-congress-could-show-100723869.html",
    "pubDate": "2024-07-09T10:07:23Z"
  },
  {
    "title": "This May Be the Most Overlooked COVID Symptom",
    "link": "https://www.yahoo.com/news/may-most-overlooked-covid-symptom-122142413.html",
    "pubDate": "2024-07-08T12:21:42Z"
  }
]